wwdata/Class_HydroData.py
wwdata/Class_LabExperimBased.py
wwdata/Class_LabSensorBased.py
wwdata/Class_OnlineSensorBased.py
wwdata/__init__.py
wwdata/data_reading_functions.py
wwdata/time_conversion_functions.py
wwdata-0.2.0.dist-info/METADATA
wwdata-0.2.0.dist-info/RECORD
wwdata-0.2.0.dist-info/WHEEL
wwdata-0.2.0.dist-info/top_level.txt
