Metadata-Version: 2.1
Name: wwdata
Version: 0.2.0
Summary: Data analysis package aimed at data obtained in the context of (waste)water
Home-page: https://github.com/UGentBIOMATH/wwdata
Author: Chaim De Mulder
Author-email: demulderchaim@gmail.com
License: GNU General Public License v3
Keywords: wwdata
Platform: UNKNOWN
Classifier: Development Status :: 2 - Pre-Alpha
Classifier: Intended Audience :: Developers
Classifier: License :: OSI Approved :: GNU General Public License v3 (GPLv3)
Classifier: Natural Language :: English
Classifier: Programming Language :: Python :: 2
Classifier: Programming Language :: Python :: 2.6
Classifier: Programming Language :: Python :: 2.7
Classifier: Programming Language :: Python :: 3
Classifier: Programming Language :: Python :: 3.3
Classifier: Programming Language :: Python :: 3.4
Classifier: Programming Language :: Python :: 3.5
Requires-Dist: pandas
Requires-Dist: numpy
Requires-Dist: dateutils
Requires-Dist: scipy
Requires-Dist: matplotlib
Requires-Dist: statsmodels
Requires-Dist: xlrd
